limin_bench/__init__.py
limin_bench/application_run.py
limin_bench/base.py
limin_bench/datasets.py
limin_bench/evaluation_run.py
limin_bench/model_run.py
limin_bench/data/mt_bench.json
limin_bench-0.3.1.dist-info/METADATA
limin_bench-0.3.1.dist-info/WHEEL
limin_bench-0.3.1.dist-info/top_level.txt
limin_bench-0.3.1.dist-info/RECORD
