Metadata-Version: 2.4
Name: limin-bench
Version: 0.3.1
Summary: A Python library for benchmarking and evaluating LLMs.
Author-email: Titanom Solutions <infrastructure@titanom.com>
Requires-Python: >=3.10
Requires-Dist: limin>=0.9.1
Requires-Dist: limin-talk>=0.2.0
